{
  "item_id": "U-01",
  "item_name": "root 계정 원격 접속 제한",
  "inspection": {
    "summary": "SSH/Telnet 서비스 미사용으로 root 원격 접속 불가",
    "status": "양호"
  },
  "final_result": "GOOD",
  "command": "service ssh status; service telnetd/inetd/xinetd status",
  "command_result": "[SSH Service Status]\\n/c/Users/uhyan/Desktop/yuh/KISA-CIIP-2026-dev/public/01.Unix서버/Debian/U01_check.sh: line 166: systemctl: command not found\\n/c/Users/uhyan/Desktop/yuh/KISA-CIIP-2026-dev/public/01.Unix서버/Debian/U01_check.sh: line 166: service: command not found\\n\\n[Telnet Service Status]\\n/c/Users/uhyan/Desktop/yuh/KISA-CIIP-2026-dev/public/01.Unix서버/Debian/U01_check.sh: line 166: systemctl: command not found\\n/c/Users/uhyan/Desktop/yuh/KISA-CIIP-2026-dev/public/01.Unix서버/Debian/U01_check.sh: line 166: service: command not found\\nTelnet service not found",
  "guideline": {
    "purpose": "root 계정의 원격 접속 제한을 통한 무단 접근 및 권한 상승 방지",
    "security_threat": "root 계정 원격 접속이 허용될 경우 비인가자가 root 권한을 획득하여 시스템 장악 및 중요 정보 유출 위험",
    "judgment_criteria_good": "PermitRootLogin no 설정 또는 원격 접속 차단된 경우",
    "judgment_criteria_bad": " root 계정 원격 접속이 가능한 경우 / N/A: SSH/Telnet 서비스 미사용",
    "remediation": "SSH 설정 파일에서 PermitRootLogin no 설정 및 /etc/securetty에서 pts 제거"
  },
  "timestamp": "2026-03-31T20:57:30+09:00",
  "hostname": "nacsc"
}
